MANIFEST.in
README.md
kiseru.py
setup.py
kiseru.egg-info/PKG-INFO
kiseru.egg-info/SOURCES.txt
kiseru.egg-info/dependency_links.txt
kiseru.egg-info/top_level.txt