Metadata-Version: 1.1
Name: kiseru
Version: 0.0.1
Summary: Make any your functions pipable.
Home-page: https://github.com/mtwtkman/kiseru
Author: mtwtkman
Author-email: UNKNOWN
License: WTFPL
Keywords: pipe
Platform: UNKNOWN
Classifier: Programming Language :: Python
